socialgathering/facebook/__init__.py
socialgathering/facebook/__main__.py
socialgathering/facebook/constants.py
socialgathering/facebook/exceptions.py
socialgathering/facebook/extractors.py
socialgathering/facebook/facebook_scraper.py
socialgathering/facebook/fb_types.py
socialgathering/facebook/page_iterators.py
socialgathering/facebook/utils.py
socialgathering/twitter/__init__.py
socialgathering-0.0.4.dist-info/LICENSE
socialgathering-0.0.4.dist-info/METADATA
socialgathering-0.0.4.dist-info/WHEEL
socialgathering-0.0.4.dist-info/top_level.txt
socialgathering-0.0.4.dist-info/RECORD
