Metadata-Version: 2.1
Name: socialgathering
Version: 0.0.4
Summary: Powerful Person and Company Enrichment
Home-page: https://github.com/
Author: Atif Raza Chaudary
Author-email: atifr454@gmail.com
Project-URL: Bug Tracker, https://github.com/issues
Classifier: Programming Language :: Python :: 3
Classifier: License :: OSI Approved :: MIT License
Classifier: Operating System :: OS Independent
Requires-Python: >=3.6
License-File: LICENSE
